[{"title": "공산당 105주년 맞아 강한 군대·대만 통일 강조한 시진핑", "link": "https://www.hankyung.com/article/202607019243i", "pubDate": "Wed, 01 Jul 2026 13:03:04 +0900", "author": "김은정", "description": "", "thumbnail": ""}, {"title": "부동산 개발서 임대 운영으로…中 지방 국유기업의 변신", "link": "https://www.hankyung.com/article/202605308172i", "pubDate": "Wed, 01 Jul 2026 13:00:03 +0900", "author": "김은정", "description": "", "thumbnail": ""}, {"title": "첫 '원청 상대 하청노조 파업' 눈앞…건설플랜트노조 파업 투표 가결", "link": "https://www.hankyung.com/article/202607019232i", "pubDate": "Wed, 01 Jul 2026 12:40:27 +0900", "author": "곽용희", "description": "", "thumbnail": ""}, {"title": "'유령도시'가 된 중국 신도시…\"싼 집세에 청년층 유입\"", "link": "https://www.hankyung.com/article/202607019211i", "pubDate": "Wed, 01 Jul 2026 12:31:59 +0900", "author": "김동현", "description": "", "thumbnail": ""}, {"title": "[속보] 시진핑 \"대만독립세력 타격, 통일 굳건히 추진할 것\"", "link": "https://www.hankyung.com/article/2026070192277", "pubDate": "Wed, 01 Jul 2026 12:22:46 +0900", "author": "신용현", "description": "", "thumbnail": ""}, {"title": "트럼프 관세 재건 맡은 그리어…美 무역정책 '실세' 부상", "link": "https://www.hankyung.com/article/202607018269i", "pubDate": "Wed, 01 Jul 2026 12:02:54 +0900", "author": "김동현", "description": "", "thumbnail": ""}, {"title": "[인사] 하나증권", "link": "https://www.hankyung.com/article/2026070191946", "pubDate": "Wed, 01 Jul 2026 12:01:32 +0900", "author": "한경우", "description": "", "thumbnail": ""}, {"title": "\"시즌2가 가장 재밌다는 불문율\"…'모솔연애2' 이을까 [김소연의 현장노트]", "link": "https://www.hankyung.com/article/202607018867H", "pubDate": "Wed, 01 Jul 2026 12:01:00 +0900", "author": "김소연", "description": "", "thumbnail": ""}, {"title": "[인사] NH투자증권", "link": "https://www.hankyung.com/article/2026070191686", "pubDate": "Wed, 01 Jul 2026 12:00:34 +0900", "author": "한경우", "description": "", "thumbnail": ""}, {"title": "말벗부터 응급 알림까지…혼자 사는 부모님 지키는 'AI 케어봇'", "link": "https://www.hankyung.com/article/202607018623i", "pubDate": "Wed, 01 Jul 2026 12:00:06 +0900", "author": "임다연", "description": "", "thumbnail": ""}, {"title": "공정위, 게임사에 최혜 대우 요구한 구글에 과징금 '철퇴' 예고", "link": "https://www.hankyung.com/article/202607018714i", "pubDate": "Wed, 01 Jul 2026 12:00:04 +0900", "author": "박종관", "description": "", "thumbnail": ""}, {"title": "향수 한병 어차피 다 못쓰는데…고수들만 즐긴다는 '픽셀라이프'", "link": "https://www.hankyung.com/article/202607018832i", "pubDate": "Wed, 01 Jul 2026 12:00:01 +0900", "author": "장서우", "description": "", "thumbnail": ""}, {"title": "\"체질 개선 통해 신뢰 회복\" 거래소, 코스닥 30주년 기념식 개최", "link": "https://www.hankyung.com/article/2026070191576", "pubDate": "Wed, 01 Jul 2026 11:58:42 +0900", "author": "한경우", "description": "", "thumbnail": ""}, {"title": "'몸신' 한진우 원장, 압구정에 피부 진료 특화 '더케이한진우한의원' 열어", "link": "https://www.hankyung.com/article/202607019100i", "pubDate": "Wed, 01 Jul 2026 11:53:24 +0900", "author": "이지현", "description": "", "thumbnail": ""}, {"title": "거래소 이사장 \"'다산다사' 구조로 신뢰받는 코스닥으로 거듭나게 할 것\"", "link": "https://www.hankyung.com/article/2026070191466", "pubDate": "Wed, 01 Jul 2026 11:50:24 +0900", "author": "한경우", "description": "", "thumbnail": ""}, {"title": "'모솔연애2' 서인국 \"나도 노래 고백했다 실패\"", "link": "https://www.hankyung.com/article/202607019136H", "pubDate": "Wed, 01 Jul 2026 11:48:28 +0900", "author": "김소연", "description": "", "thumbnail": ""}, {"title": "[단독] 태평양, 리걸테크 '하비' 전사 도입…11월 자체 시스템 구축도 완료", "link": "https://www.hankyung.com/article/202607018881i", "pubDate": "Wed, 01 Jul 2026 11:39:09 +0900", "author": "허란", "description": "", "thumbnail": ""}, {"title": "여의도공원, 문화·생태 품은 미래형으로 재탄생…재조성 밑그림 나왔다", "link": "https://www.hankyung.com/article/2026070190517", "pubDate": "Wed, 01 Jul 2026 11:35:27 +0900", "author": "신용현", "description": "", "thumbnail": ""}, {"title": "'퀸' 송가인이 온다", "link": "https://www.hankyung.com/article/202607018925H", "pubDate": "Wed, 01 Jul 2026 11:32:19 +0900", "author": "한국경제 | 전체뉴스", "description": "", "thumbnail": ""}, {"title": "강한나 가슴에 품은 카더가든 \"사랑보다 한단계 위 감정\"", "link": "https://www.hankyung.com/article/202607018871H", "pubDate": "Wed, 01 Jul 2026 11:31:20 +0900", "author": "김소연", "description": "", "thumbnail": ""}, {"title": "'친문' 윤건영, 민주당 적통 논쟁 두고 \"다 부질없는 거 아닌가\"", "link": "https://www.hankyung.com/article/202607018995i", "pubDate": "Wed, 01 Jul 2026 11:28:27 +0900", "author": "최해련", "description": "", "thumbnail": ""}, {"title": "지방세 전산망 마비 사태…지방세 납부 기한 3일로 연장", "link": "https://www.hankyung.com/article/202607019044i", "pubDate": "Wed, 01 Jul 2026 11:24:00 +0900", "author": "안재광", "description": "", "thumbnail": ""}, {"title": "하이트진로, 이번엔 '25% 칼로리 다운'…\"더 순하고 가볍게\"", "link": "https://www.hankyung.com/article/202607018998g", "pubDate": "Wed, 01 Jul 2026 11:23:59 +0900", "author": "박상경", "description": "", "thumbnail": ""}, {"title": "사상 첫 월 1000억달러 돌파…美-中-獨 이어 '세계 4번째' 대기록", "link": "https://www.hankyung.com/article/202607019049i", "pubDate": "Wed, 01 Jul 2026 11:23:19 +0900", "author": "김리안", "description": "", "thumbnail": ""}, {"title": "집 사려고 주식 다 팔았다…'동탄 폭주' 이유가 있었다", "link": "https://www.hankyung.com/article/202607019033i", "pubDate": "Wed, 01 Jul 2026 11:21:10 +0900", "author": "이유정", "description": "", "thumbnail": ""}, {"title": "외국인들 앞다퉈 지갑 연다…한국서 난리 난 '뜻밖의 핫플' [트렌드+]", "link": "https://www.hankyung.com/article/202606306813g", "pubDate": "Wed, 01 Jul 2026 11:21:09 +0900", "author": "박상경", "description": "", "thumbnail": ""}, {"title": "금융위원장 \"코스닥, 성장주 투자 종착지로 도약하도록 체질 개선 추진\"", "link": "https://www.hankyung.com/article/2026070190046", "pubDate": "Wed, 01 Jul 2026 11:14:43 +0900", "author": "한경우", "description": "", "thumbnail": ""}, {"title": "와이바이오로직스 박영우 대표, 자사주 2억2700만원어치 장내매수", "link": "https://www.hankyung.com/article/202607018723i", "pubDate": "Wed, 01 Jul 2026 11:14:02 +0900", "author": "이우상", "description": "", "thumbnail": ""}, {"title": "렌털 시장 진출한 퍼시스…사무실 운영·관리도 해준다", "link": "https://www.hankyung.com/article/202607018900i", "pubDate": "Wed, 01 Jul 2026 11:11:38 +0900", "author": "민지혜", "description": "", "thumbnail": ""}, {"title": "[속보] 韓총리 \"대한민국 대격변 주도국으로…정부속도 올리는데 최선\"", "link": "https://www.hankyung.com/article/2026070189887", "pubDate": "Wed, 01 Jul 2026 11:08:14 +0900", "author": "신용현", "description": "", "thumbnail": ""}, {"title": "'김비서'·'시그널'…K-드라마, 태국 찍고 인도까지 수출", "link": "https://www.hankyung.com/article/202607018923H", "pubDate": "Wed, 01 Jul 2026 11:01:29 +0900", "author": "김소연", "description": "", "thumbnail": ""}, {"title": "\"아직 마음의 준비 안돼\"…광주일고, 배재고 사과 거절", "link": "https://www.hankyung.com/article/2026070188887", "pubDate": "Wed, 01 Jul 2026 11:01:27 +0900", "author": "신용현", "description": "", "thumbnail": ""}, {"title": "안철수 \"반도체 초과세수, 호남에 무제한 투입될 수 있다\"", "link": "https://www.hankyung.com/article/2026070187307", "pubDate": "Wed, 01 Jul 2026 11:00:54 +0900", "author": "신현보", "description": "", "thumbnail": ""}, {"title": "그룹사 1.2조 유증에 8% 떨어진 에코프로…초고수는 '줍줍'", "link": "https://www.hankyung.com/article/202607018473i", "pubDate": "Wed, 01 Jul 2026 11:00:05 +0900", "author": "양지윤", "description": "", "thumbnail": ""}, {"title": "대구오페라축제, 시민 홍보단 '오페라팬' 11기 발대식 개최", "link": "https://www.hankyung.com/article/202607018405i", "pubDate": "Wed, 01 Jul 2026 10:59:33 +0900", "author": "조동균", "description": "", "thumbnail": ""}, {"title": "김민석 \"정청래 굳이 두 번 할 필요 있나\" 연임론에 제동", "link": "https://www.hankyung.com/article/2026070186007", "pubDate": "Wed, 01 Jul 2026 10:59:24 +0900", "author": "김희선", "description": "", "thumbnail": ""}, {"title": "\"애국가에서 홍명보 당장 삭제해야\" 사퇴에도 들끓는 여론", "link": "https://www.hankyung.com/article/2026070188457", "pubDate": "Wed, 01 Jul 2026 10:58:44 +0900", "author": "이미나", "description": "", "thumbnail": ""}, {"title": "[속보] 행안부 \"지방세서비스 장애 업무지연…납부기한 3일까지 연장\"", "link": "https://www.hankyung.com/article/2026070189247", "pubDate": "Wed, 01 Jul 2026 10:54:21 +0900", "author": "신용현", "description": "", "thumbnail": ""}, {"title": "해외도 놀란 'K반도체 초대형 베팅'…\"호황기 지나면 공급과잉\" 경고도", "link": "https://www.hankyung.com/article/202607018479g", "pubDate": "Wed, 01 Jul 2026 10:53:35 +0900", "author": "김대영", "description": "", "thumbnail": ""}, {"title": "전장연 '버스 탑승 시위'에 출근길 혼잡…내일은 지하철 예고", "link": "https://www.hankyung.com/article/202607018831i", "pubDate": "Wed, 01 Jul 2026 10:50:58 +0900", "author": "우연수", "description": "", "thumbnail": ""}, {"title": "룰루레몬, 서소문서 요가 행사 '스페이스 투 필' 연다", "link": "https://www.hankyung.com/article/202607018526i", "pubDate": "Wed, 01 Jul 2026 10:46:40 +0900", "author": "안혜원", "description": "", "thumbnail": ""}, {"title": "[속보] 지방세시스템 '위택스' 서비스 장애…납부 차질", "link": "https://www.hankyung.com/article/2026070188937", "pubDate": "Wed, 01 Jul 2026 10:46:28 +0900", "author": "신용현", "description": "", "thumbnail": ""}, {"title": "창업주가 판 위메이드…주가 상한가 치는 이유는", "link": "https://www.hankyung.com/article/202607018828i", "pubDate": "Wed, 01 Jul 2026 10:44:45 +0900", "author": "허진", "description": "", "thumbnail": ""}, {"title": "편지 한 통 430원에서 500원으로…5년 만의 요금 인상", "link": "https://www.hankyung.com/article/2026070188357", "pubDate": "Wed, 01 Jul 2026 10:44:14 +0900", "author": "신용현", "description": "", "thumbnail": ""}, {"title": "\"결정문도 안 줬다\"…내란특검·종합특검, 갈등 봉합은커녕 확전", "link": "https://www.hankyung.com/article/202607018790i", "pubDate": "Wed, 01 Jul 2026 10:37:58 +0900", "author": "임민규", "description": "", "thumbnail": ""}, {"title": "달고기전·배추전 한상에…李대통령, 文 청와대 초청 오찬 메뉴는", "link": "https://www.hankyung.com/article/2026070187477", "pubDate": "Wed, 01 Jul 2026 10:37:15 +0900", "author": "김희선", "description": "", "thumbnail": ""}, {"title": "LX하우시스, PF 단열재 특허 소송서 최종 승소했다", "link": "https://www.hankyung.com/article/202607018815i", "pubDate": "Wed, 01 Jul 2026 10:34:08 +0900", "author": "민지혜", "description": "", "thumbnail": ""}, {"title": "편의점도 웰니스 트렌드…이마트24, 고단백·저당 '가뿐한입' 론칭", "link": "https://www.hankyung.com/article/202607018571g", "pubDate": "Wed, 01 Jul 2026 10:32:18 +0900", "author": "박상경", "description": "", "thumbnail": ""}, {"title": "'불꽃야구' 배재고 편 방송 취소…'스타벅스 가야지' 사태 일파만파", "link": "https://www.hankyung.com/article/2026070188127", "pubDate": "Wed, 01 Jul 2026 10:32:00 +0900", "author": "김예랑", "description": "", "thumbnail": ""}, {"title": "국민·기업은행, 전북 서남권 해상풍력 금융자문 맡는다", "link": "https://www.hankyung.com/article/202607018829i", "pubDate": "Wed, 01 Jul 2026 10:30:43 +0900", "author": "김진성", "description": "", "thumbnail": ""}]