[{"title": "준중형 중고차 판매량 1위는 바로 ‘이 차’", "link": "https://www.mk.co.kr/news/economy/12060984", "pubDate": "Fri, 29 May 2026 11:26:56 +09:00", "author": "매일경제", "description": "KB캐피탈이 운영하는 중고차 거래 플랫폼 ‘KB차차차’는 2025년 5월부터 2026년 4월까지 자사 플랫폼에서 판매된 준중형 차량 판매량을 분석한 결과 현대 아반떼가 1위를 차지..", "thumbnail": "https://pimg.mk.co.kr/news/cms/202605/29/news-p.v1.20260529.01fa34f9d0b54bdda46211cda42a288b_R.jpg"}, {"title": "“K뷰티는 이제 미래산업” 구윤철 부총리, 한국콜마 종합기술원 방문", "link": "https://www.mk.co.kr/news/economy/12060907", "pubDate": "Fri, 29 May 2026 10:43:34 +09:00", "author": "매일경제", "description": "한국콜마, CES2026 최고혁신상 계기 뷰티테크 산업 지원 관련 간담회도 개최구윤철 경제부총리 겸 재정경제부 장관이 한국콜마를 방문했다. 28일 서울 서초구 소재 한국콜마 종합기..", "thumbnail": "https://pimg.mk.co.kr/news/cms/202605/29/news-p.v1.20260529.02b304eb5f544011ad8c5679eca02834_R.jpg"}, {"title": "AI 시대 인재상은?…최태원이 답했다 “스페셜보단 제너럴리스트형”", "link": "https://www.mk.co.kr/news/economy/12060851", "pubDate": "Fri, 29 May 2026 09:49:33 +09:00", "author": "매일경제", "description": "“AI 시대 인재의 정의 달라질 것… AI가 못하는 인간만의 경쟁력 키워야“ 생각·공감·적응·바디스킬 등 ‘4가지 근육’ 제시최태원 SK그룹 회장 겸 대한상공회의소 회장이 “인공지..", "thumbnail": "https://pimg.mk.co.kr/news/cms/202605/29/news-p.v1.20260529.5b5a7abbcf524993b317400e94a7d044_R.jpg"}, {"title": "[속보] 4월 산업생산 0.6%↓·소비 3.6%↓·투자 3.6%↓…‘트리플 감소’", "link": "https://www.mk.co.kr/news/economy/12060749", "pubDate": "Fri, 29 May 2026 08:01:36 +09:00", "author": "매일경제", "description": "지난달 국내 생산과 소비, 투자가 일제히 감소한 것으로 나타났다. 이른바 ‘트리플 감소’는 작년 8월 이후 8개월 만이다. 올해 2월 말 발발한 중동 전쟁의 충격이 시차를 두고 4..", "thumbnail": "https://pimg.mk.co.kr/news/cms/202605/29/news-p.v1.20260529.ade230b73e2442f3a54fecc7cbcdb55d_R.jpg"}, {"title": "은행도 주식으로 돈 번다…4대銀 ETF 판매액 40조, 수수료 급증", "link": "https://www.mk.co.kr/news/economy/12060742", "pubDate": "Fri, 29 May 2026 07:26:12 +09:00", "author": "매일경제", "description": "1~5월 판매액 벌써 작년 2배 수수료율 인상·차등화 전략도국내 상장지수펀드(ETF) 판매액이 40조원을 돌파하면서 ETF 신탁수수료가 은행권의 새 수익원으로 떠오르고 있다. 이런..", "thumbnail": "https://pimg.mk.co.kr/news/cms/202605/29/news-p.v1.20250707.3eb2c493f3a7469fb8a8d8d2ea7b5f18_R.png"}, {"title": "“다시 맞벌이해 볼까?” … ‘일하면 손해’ 국민연금은 이제  옛말", "link": "https://www.mk.co.kr/news/economy/12060025", "pubDate": "Fri, 29 May 2026 05:00:00 +09:00", "author": "매일경제", "description": "6월부터 月 500만원 벌어도 국민연금 안 깎여“은퇴 후 생활비가 부족해서 일 좀 했다고, 국민연금을 깎아 버리는 게 이해가 안 돼요.”(60대 A씨) 그동안 국민연금 감액 통지를..", "thumbnail": "https://pimg.mk.co.kr/news/cms/202605/28/rcv.YNA.20231213.PYH2023121308250001300_R.jpg"}, {"title": "8연속 금리동결 바통받은 신현송…‘연내인상’ 매의 발톱 드러냈다", "link": "https://www.mk.co.kr/news/economy/12060585", "pubDate": "Thu, 28 May 2026 23:47:22 +09:00", "author": "매일경제", "description": "한은, 금리 동결속 깜짝 ‘인상’ 예고 점도표 상단 3.0%로 이동 신현송 총재 첫 금통위 주재 “금통위 위원 인식 일치했다” 매파적 메시지에 채권 ‘긴축 발작’“이번 금융통화위원..", "thumbnail": "https://pimg.mk.co.kr/news/cms/202605/28/rcv.YNA.20260528.PYH2026052810500001300_R.jpg"}, {"title": "물장 뚫고 나온 불기둥 LG엔솔…‘2.4조 계약’에 15% 급등", "link": "https://www.mk.co.kr/news/economy/12060566", "pubDate": "Thu, 28 May 2026 23:00:25 +09:00", "author": "매일경제", "description": "美에너지사 ‘DTE에너지’와 계약 오라클 데이터센터 전력인프라에 2026~2027년 ESS 배터리 납품 급성장 美 AI데이터센터 수요공략 연내 북미 생산능력 50GWh 목표LG에너..", "thumbnail": "https://pimg.mk.co.kr/news/cms/202605/28/news-p.v1.20260528.e2236ef4c0bb410db238bbf70b2e7575_R.png"}, {"title": "“몇천씩 벌었다니 안 할 수가”…‘빚투’ 광풍, 신용대출 2조 급증", "link": "https://www.mk.co.kr/news/economy/12060518", "pubDate": "Thu, 28 May 2026 21:55:17 +09:00", "author": "매일경제", "description": "코로나19 이후 月증가폭 최대 잔액도 2년반만에 최대규모 가계대출 총량 규제에 눌리다 역대급 증시 랠리에 다시 폭증 금리 상단 6% 육박해도 ‘빚투’코스피 급등장 속 ‘빚투(빚내서..", "thumbnail": "https://pimg.mk.co.kr/news/cms/202605/28/news-g.v1.20260528.fc0f78519bb94772adef86f82b953b79_R.jpg"}, {"title": "“혹시 실손보험 있나요?”…앞으로 환자 유인땐 의사 면허 6개월 정지", "link": "https://www.mk.co.kr/news/economy/12060460", "pubDate": "Thu, 28 May 2026 20:47:29 +09:00", "author": "매일경제", "description": "‘의료법 시행령 및 행정처분 규칙 개정안’ 입법예고앞으로 실손의료보험 혜택을 받을 수 있다고 허위·과장광고를 하며 환자를 끌어모으는 의료기관은 최대 6개월간 문을 닫아야 한다. 2..", "thumbnail": "https://pimg.mk.co.kr/news/cms/202605/28/news-p.v1.20260528.7f8097d8d6ea48c0b6eb64b0244d8e6b_R.jpg"}, {"title": "국민연금 국내 주식 비중 20.8%", "link": "https://www.mk.co.kr/news/economy/12060459", "pubDate": "Thu, 28 May 2026 20:46:18 +09:00", "author": "매일경제", "description": "국민연금이 국내 주식 목표 비중을 기존 14.9%에서 20.8%로 5.9%포인트 올리기로 결정했다. \n국민연금기금운용위원회는 28일 정부서울청사에서 2026년도 제5차 회의를 열고..", "thumbnail": ""}, {"title": "휴전, 사실상 붕괴…미국·이란 상호공습에 종전협상 다시 안갯속", "link": "https://www.mk.co.kr/news/economy/12060453", "pubDate": "Thu, 28 May 2026 20:39:40 +09:00", "author": "매일경제", "description": "미국, 휴전에도 3일만에 또 폭격 혁명수비대도 미군 추가 공습 반격 쿠웨이트 영공서 미사일 공격 포착 트럼프 내각회의서 강경 발언 “협상 만족할 수준 아냐” 호르무즈·이란 제재·핵..", "thumbnail": "https://pimg.mk.co.kr/news/cms/202605/28/rcv.YNA.20260528.PAF20260528165901009_R.jpg"}, {"title": "KB·농협·IBK·토스·지방銀 연합군 만든다 … '두나무 동맹'에 맞불", "link": "https://www.mk.co.kr/news/economy/12060450", "pubDate": "Thu, 28 May 2026 20:34:21 +09:00", "author": "매일경제", "description": "하나금융그룹이 두나무·삼성금융 등과 함께 연합군을 형성한 가운데 리딩뱅크인 KB금융도 초대형 은행권 코인 동맹을 결성하기 위한 물밑 작업에 나섰다. 디지털자산기본법 제정 논의가 속..", "thumbnail": ""}, {"title": "넉달만에 국장 목표비중 추가 상향 … 180조 매도부담 덜었다", "link": "https://www.mk.co.kr/news/economy/12060442", "pubDate": "Thu, 28 May 2026 20:26:30 +09:00", "author": "매일경제", "description": "국민연금기금운용위원회가 5개월 사이에 두 차례나 국내 주식 목표 비중을 높여 잡은 것은 전례가 없는 일이다. 지난 1월 국내 주식 목표 비중을 14.4%에서 14.9%로 높였는데,..", "thumbnail": "https://pimg.mk.co.kr/news/cms/202605/29/20260529_01160120000004_L00.jpg"}, {"title": "국민성장펀드 나흘만에 99.9% 판매…4억2000만원 남은 곳, 어디길래", "link": "https://www.mk.co.kr/news/economy/12060369", "pubDate": "Thu, 28 May 2026 19:07:01 +09:00", "author": "매일경제", "description": "금융당국은 국민참여형성장펀드 출시 나흘째인 28일 전체 물량의 약 99.9%가 판매됐다고 밝혔다. 국민성장펀드는 정부와 민간이 공동 조성하는 초대형 정책펀드로, 인공지능(AI)·반..", "thumbnail": "https://pimg.mk.co.kr/news/cms/202605/28/news-p.v1.20260528.393673a538d74004ad133a4cc87a0f56_R.jpg"}, {"title": "국민성장펀드, 퓨리오사에 8000억 투자", "link": "https://www.mk.co.kr/news/economy/12060351", "pubDate": "Thu, 28 May 2026 19:01:33 +09:00", "author": "매일경제", "description": "국민성장펀드가 국산 인공지능(AI) 반도체 개발을 지원하기 위해 퓨리오사AI에 8000억원 안팎을 직접 지분투자한다. 또 스마일게이트의 AI 데이터센터 건설에 5000억원, SK바..", "thumbnail": "https://pimg.mk.co.kr/news/cms/202605/29/20260529_01160112000002_L00.jpg"}, {"title": "“이러다 시총 1위 뒤바뀌는 거 아냐”…삼전 ‘뛸때’ 하이닉스 977% 날았다", "link": "https://www.mk.co.kr/news/economy/12060340", "pubDate": "Thu, 28 May 2026 18:47:50 +09:00", "author": "매일경제", "description": "SK하닉, 삼전과 시총 격차 6.8% 바짝 추격SK하이닉스가 국내 시총 1위를 넘보며 삼성전자를 바짝 추격하고 있는 것으로 나타났다. 28일 기업분석전문 한국CXO연구소에 따르면 ..", "thumbnail": "https://pimg.mk.co.kr/news/cms/202605/28/news-p.v1.20260528.1960d878fe194dedb60062d94c70a870_R.jpg"}, {"title": "워시가 낮은 금리 아닌 ‘작은 연준’을 말하는 까닭", "link": "https://www.mk.co.kr/news/economy/12060336", "pubDate": "Thu, 28 May 2026 18:41:29 +09:00", "author": "매일경제", "description": "막 오른 케빈 워시 시대 ②케빈 워시 미국 연방준비제도 의장이 다음달 16~17일 첫 연방공개시장위원회를 주재한다. 시장은 이미 금리표를 들여다보고 있다. 첫 회의에서 금리를 내릴..", "thumbnail": "https://pimg.mk.co.kr/news/cms/202605/28/news-p.v1.20260522.b93f584f8cad4ce1ab6db5747a1c97fe_R.png"}, {"title": "신현송 금융안정 중시하는 매파...유동성 줄여나갈듯", "link": "https://www.mk.co.kr/news/economy/12060335", "pubDate": "Thu, 28 May 2026 18:41:07 +09:00", "author": "매일경제", "description": "신현송 한은총재 인물 해부 ③/ 향후 통화정책 방향과 과제신현송 한국은행 총재는 매파일까 비둘기파일까.  매파는 경제 성장 보다 물가를 중시해 경기가 다소 위축되더라도 금리 인상을..", "thumbnail": "https://pimg.mk.co.kr/news/cms/202605/28/news-a.v1.20260527.93106dbfde884827a34cb2302d8b7e84_R.png"}, {"title": "신현송 '매파적 동결'… \"금리인상 필요\"", "link": "https://www.mk.co.kr/news/economy/12060297", "pubDate": "Thu, 28 May 2026 18:08:39 +09:00", "author": "매일경제", "description": "한국은행 금융통화위원회가 28일 기준금리를 연 2.50%로 유지하기로 결정했다. 지난해 7월 이후 8회 연속 동결이다.\n중동 전쟁으로 고환율·고유가·고물가 등 '3고' 압박이 커지..", "thumbnail": "https://pimg.mk.co.kr/news/cms/202605/29/20260529_01160101000003_L00.jpg"}, {"title": "[속보] 국민연금, 올해 국내주식 목표 비중 14.9%→20.8%로 확대", "link": "https://www.mk.co.kr/news/economy/12060289", "pubDate": "Thu, 28 May 2026 18:04:26 +09:00", "author": "매일경제", "description": "국민연금이 올해 국내주식 보유목표 비중을 기존 14.9%에서 20.8%로 확대키로 했다. 국민연금 기금운용위원회는 28일 오후 제5차 국민연금 기금운용위원회를 열고 이러한 내용이 ..", "thumbnail": "https://pimg.mk.co.kr/news/cms/202605/28/news-p.v1.20260528.b0195d49e9444d62af5b7466a7b534dc_R.jpg"}, {"title": "[포토] 금융위, 매입채권추심업 허가제 전환", "link": "https://www.mk.co.kr/news/economy/12060275", "pubDate": "Thu, 28 May 2026 18:01:07 +09:00", "author": "매일경제", "description": "", "thumbnail": "https://pimg.mk.co.kr/news/cms/202605/29/20260529_01110112000007_L00.jpg"}, {"title": "[표] 당좌거래정지", "link": "https://www.mk.co.kr/news/economy/12060272", "pubDate": "Thu, 28 May 2026 18:01:06 +09:00", "author": "매일경제", "description": "", "thumbnail": "https://pimg.mk.co.kr/news/cms/202605/29/20260529_01110112000004_L00.jpg"}, {"title": "4대은행 ETF 판매 40조 돌파 … 수수료 수익 극대화 전략 골몰", "link": "https://www.mk.co.kr/news/economy/12060273", "pubDate": "Thu, 28 May 2026 18:01:06 +09:00", "author": "매일경제", "description": "국내 상장지수펀드(ETF) 판매액이 40조원을 돌파하면서 ETF 신탁수수료가 은행권의 새 수익원으로 떠오르고 있다. 이런 가운데 일부 은행은 관련 수수료를 인상하며 수익성 강화에 ..", "thumbnail": "https://pimg.mk.co.kr/news/cms/202605/29/20260529_01110112000005_S00.jpg"}, {"title": "[표] 외국환율고시표", "link": "https://www.mk.co.kr/news/economy/12060274", "pubDate": "Thu, 28 May 2026 18:01:06 +09:00", "author": "매일경제", "description": "", "thumbnail": "https://pimg.mk.co.kr/news/cms/202605/29/20260529_01110112000006_L00.jpg"}, {"title": "\"금리 올라도 빚투\"…신용대출 한달새 3조↑", "link": "https://www.mk.co.kr/news/economy/12060270", "pubDate": "Thu, 28 May 2026 18:01:05 +09:00", "author": "매일경제", "description": "코스피 급등장 속 '빚투(빚내서 투자)' 열풍이 다시 거세지면서 은행권 신용대출이 빠르게 불어나고 있다. 특히 신용대출 금리가 5%대 후반까지 올라선 상황에서도 대출 수요가 오히려..", "thumbnail": "https://pimg.mk.co.kr/news/cms/202605/29/20260529_01160112000001_L00.jpg"}, {"title": "화재보험협회 이사장에 김기환 전 KB손보 대표", "link": "https://www.mk.co.kr/news/economy/12060271", "pubDate": "Thu, 28 May 2026 18:01:05 +09:00", "author": "매일경제", "description": "김기환 전 KB손해보험 대표가 차기 화재보험협회 이사장으로 내정됐다. \n28일 보험업계에 따르면 화재보험협회 이사장후보추천위원회는 차기 이사장 후보 3명에 대해 최종 면접을 진행한..", "thumbnail": ""}, {"title": "\"농촌기본소득 연내 법제화…재생에너지 수익 활용\"", "link": "https://www.mk.co.kr/news/economy/12060235", "pubDate": "Thu, 28 May 2026 17:54:49 +09:00", "author": "매일경제", "description": "송미령 농림축산식품부 장관이 농어촌 소멸의 핵심 대안인 '농어촌 기본소득' 시범사업을 연내 법제화하겠다고 밝혔다. 단순 복지 지원을 넘어 재생에너지 수익을 재원으로 자생적 경제 모..", "thumbnail": "https://pimg.mk.co.kr/news/cms/202605/29/20260529_01110110000004_L00.jpg"}, {"title": "한은, 금리인상 '깜빡이' … 점도표 절반이 6개월뒤 3% 전망", "link": "https://www.mk.co.kr/news/economy/12060233", "pubDate": "Thu, 28 May 2026 17:54:48 +09:00", "author": "매일경제", "description": "\"이번 금융통화위원회 회의는 의견을 모으기 쉬웠다. 금통위원들 간 인식이 대체로 같았다.\"\n신현송 한국은행 총재는 28일 통화정책방향 회의 직후 기자간담회에서 이같이 말했다. 이날..", "thumbnail": "https://pimg.mk.co.kr/news/cms/202605/29/20260529_01160110000002_L00.jpg"}, {"title": "\"韓, 전세계 수출 5강으로…올 9000억달러 돌파\"", "link": "https://www.mk.co.kr/news/economy/12060234", "pubDate": "Thu, 28 May 2026 17:54:48 +09:00", "author": "매일경제", "description": "김정관 산업통상부 장관이 \"올해 수출이 9000억달러를 넘을 것이라고 조심스럽게 예상한다\"며 \"전 세계 수출 5강을 달성할 수 있을 것으로 보인다\"고 강조했다. \n지난해 수출(70..", "thumbnail": "https://pimg.mk.co.kr/news/cms/202605/29/20260529_01160110000001_M00.jpg"}, {"title": "상위 20% 1238만원…하위 20% 117만원", "link": "https://www.mk.co.kr/news/economy/12060193", "pubDate": "Thu, 28 May 2026 17:38:07 +09:00", "author": "매일경제", "description": "올해 1분기 소득 상위 20% 가구의 월평균 소득이 처음으로 1200만원을 돌파했다. \n대기업의 성과급 잔치로 고소득층의 소득이 급증한 대목이다. 하지만 중산층과 저소득층의 소득은..", "thumbnail": ""}, {"title": "“나라곳간 채운 공공기관의 배당”… 2.8조 역대 최대 ‘세수 효자’", "link": "https://www.mk.co.kr/news/economy/12060092", "pubDate": "Thu, 28 May 2026 16:38:43 +09:00", "author": "매일경제", "description": "평균 배당성향도 40.9% 최고치 산은·수은 등 금융공기업 견인 정부, 향후 5년 목표 재설정 검토정부가 출자한 공공기관으로부터 받는 배당금이 올해 2조8000억원에 육박하며 역대..", "thumbnail": "https://pimg.mk.co.kr/news/cms/202605/28/news-p.v1.20260102.64b464a77bc64d58ae3c25bf0f542466_R.jpg"}, {"title": "상위 20% 가구 월소득 1200만 첫 돌파… 성과급이 가른 ‘K자형’ 양극화", "link": "https://www.mk.co.kr/news/economy/12060061", "pubDate": "Thu, 28 May 2026 16:21:56 +09:00", "author": "매일경제", "description": "국가데이터처, 1분기 가계동향조사  5분위 배율 6.59배 ‘6년 만에 최대’ 대기업·중소기업 임금 격차 심화 고소득층 年5천만원 흑자 기록때 서민층 자산 형성 기회 실종한 듯 삼..", "thumbnail": "https://pimg.mk.co.kr/news/cms/202605/28/rcv.NEWSIS.NEWSIS.20260409.NISI20260409_0021240660_R.jpg"}, {"title": "송미령 “농어촌 기본소득, 연내 법제화”", "link": "https://www.mk.co.kr/news/economy/12060010", "pubDate": "Thu, 28 May 2026 15:53:19 +09:00", "author": "매일경제", "description": "농식품부 출입기자단 현장 간담회 재생에너지 전환 통한 재원확보 목표 현금살포 비판엔 “기본소득은 마중물” 시범사업 1년, 처음으로 정육점이 생겨비가 내리는 순창군 유등면. 흙냄새가..", "thumbnail": "https://pimg.mk.co.kr/news/cms/202605/28/news-p.v1.20260527.e5bef49f3c25461597838e1c4168a41d_R.jpg"}, {"title": "7월 금리 ‘인상론’ 급부상에…한은 총재 “금리 인상할 필요 있다”", "link": "https://www.mk.co.kr/news/economy/12059993", "pubDate": "Thu, 28 May 2026 15:33:38 +09:00", "author": "매일경제", "description": "한은 금통위 개최, 기준금리 8연속 동결 시장선 오는 7월 인상 가능성 전망한국은행 금융통화위원회는 28일 기준금리를 8회 연속 연 2.50%로 동결했지만, 신현송 한은 총재가 통..", "thumbnail": "https://pimg.mk.co.kr/news/cms/202605/28/news-p.v1.20260528.a007eba60b6b4f64b1cb3b8e317bc282_R.jpg"}, {"title": "유망 중기업 100개, 중견기업행 사다리 놓는다", "link": "https://www.mk.co.kr/news/economy/12059980", "pubDate": "Thu, 28 May 2026 15:26:50 +09:00", "author": "매일경제", "description": "중기부, 점프업 100개사 선정  5.3대1 경쟁률 뚫은 유망 중기 매출별 3단계 구분해 집중지원 2029년까지 500社 육성 목표 업계 “실무형 인재 매칭 시급”방사선 진단장치 ..", "thumbnail": "https://pimg.mk.co.kr/news/cms/202605/29/news-p.v1.20260528.84640bc90a6c41e5aefd06f33c7cadb6_R.jpg"}, {"title": "빚 독촉 추심업체 정리한다…매입채권추심업 구조조정 나선 금융당국", "link": "https://www.mk.co.kr/news/economy/12059973", "pubDate": "Thu, 28 May 2026 15:12:14 +09:00", "author": "매일경제", "description": "금융위 제5차 포용적 금융 대전환 회의> 이재명 대통령 ‘원시적 약탈금융’ 지적에 당국, 매입채권추심업 허가제 전환 추진 등록제로 난립해있는 추심업체들 900여곳서 30여곳으로 줄..", "thumbnail": "https://pimg.mk.co.kr/news/cms/202605/28/news-p.v1.20260528.67698c19a78640b3957b43a19846c916_R.png"}, {"title": "“직원 연봉 동결하고 사주는 슈퍼카”… 국세청, 탈세 법인 19곳 ‘정밀 타격’", "link": "https://www.mk.co.kr/news/economy/12059963", "pubDate": "Thu, 28 May 2026 15:05:26 +09:00", "author": "매일경제", "description": "국세청, 슈퍼카 사적 사용 19개 법인 세무조사 슈퍼카 90대 소유…탈루혐의 액수 총 3000억원 법인 자금, 통행세 거래·룸살롱 사용 등도 적발 국세청 “사주 일가·관련 기업까지..", "thumbnail": "https://pimg.mk.co.kr/news/cms/202605/28/rcv.NEWS1.NEWS1.20260528.2026-05-28T122200_1007929620_SOCIETY_I_R.jpg"}, {"title": "반려동물 물로 장례하는 ‘수분해장’...4년前 법은 마련, 기준은 ‘깜깜이’", "link": "https://www.mk.co.kr/news/economy/12059708", "pubDate": "Thu, 28 May 2026 14:08:00 +09:00", "author": "매일경제", "description": "사체를 화학용액으로 녹이는 방식 대기 오염 없어 미국 등 16개서 시행 4년전 동물보호법 규칙 개정했는데  ‘시설·설치 기준 고시’는 여전히 없어  네오메이션 “기술 있지만, 상용..", "thumbnail": "https://pimg.mk.co.kr/news/cms/202605/28/news-p.v1.20230809.aa819a47d5b74560b7a3362c1d241fe5_R.jpg"}, {"title": "반도체 수요는 당분간 꾸준히 증가…가격 상승세 지속된다는데", "link": "https://www.mk.co.kr/news/economy/12059811", "pubDate": "Thu, 28 May 2026 13:49:53 +09:00", "author": "매일경제", "description": "한은, 경제전망 보고서 발표 “AI 서버 수요는 확대” 전망한국은행은 올해 국내 경제가 반도체 수출이 예상을 크게 웃도는 호조세를 이어가며 경제 성장률이 전망치보다 높아질 것으로 ..", "thumbnail": "https://pimg.mk.co.kr/news/cms/202605/28/news-p.v1.20260528.50cfef59c6974983a12a780a9d796301_R.png"}, {"title": "신현송 총재 “적절 시기에 금리 인상 필요…환율 쏠림 단호히 대처”", "link": "https://www.mk.co.kr/news/economy/12059808", "pubDate": "Thu, 28 May 2026 13:48:59 +09:00", "author": "매일경제", "description": "한은 금통위 개최, 기준금리 8연속 동결 환율 약세, 중동 상황·외국인 리밸런싱 “중동상황 진전시, 원화 강세 여지 있어”한국은행 금융통화위원회가 28일 연 2.50%인 기준금리를..", "thumbnail": "https://pimg.mk.co.kr/news/cms/202605/28/news-p.v1.20260528.0d85a41928124464a8178b6c9d2e2978_R.jpg"}, {"title": "‘홍길동한테 돈 보냈는데 어쩌나’…금감원, 개인명의 사칭 ‘삼행시 단체통장’ 주의보 발령", "link": "https://www.mk.co.kr/news/economy/12059784", "pubDate": "Thu, 28 May 2026 13:32:04 +09:00", "author": "매일경제", "description": "개인 이름처럼 보이는 삼행시로 임의단체명 짓고 계좌를 개설하는 일명 ‘삼행시 단체통장’에 대해 금융감독원이 소비자경보(주의 단계)를 28일 발령했다. 임의단체의 계좌는 각종 사기나..", "thumbnail": "https://pimg.mk.co.kr/news/cms/202605/28/news-p.v1.20260528.4d18a2f6b51149f4b1c9ab7db840d1d2_R.png"}, {"title": "“가전도 이제 AI 제조”… 정부, ‘M.AX’ 3대 과제 가속", "link": "https://www.mk.co.kr/news/economy/12059779", "pubDate": "Thu, 28 May 2026 13:19:30 +09:00", "author": "매일경제", "description": "산업부, 가전 제조 특화 AI 모델 개발 착수 AI가 물류 관리하는 가전 전용 모델 구축 학습 데이터 확보 로드맵도 구축하고 AI 가전 인증 기준 마련해 소비자도 보호정부가 가전 ..", "thumbnail": "https://pimg.mk.co.kr/news/cms/202605/28/news-p.v1.20251224.9f027d8a13d84459b20fb1f25d4b81fc_R.png"}, {"title": "금융인재개발원, 회계실무자윤리인증 과정 운영…“상장사 리스크 선제 대응”", "link": "https://www.mk.co.kr/news/economy/12059769", "pubDate": "Thu, 28 May 2026 12:29:52 +09:00", "author": "매일경제", "description": "금융당국 ‘포괄적 재량권’ 도입 추진 중대 회계 부정 즉각 퇴출 시대 개막금융당국이 중대 회계 부정을 저지른 상장사에 대한 즉각 퇴출 방안을 추진중인 가운데 회계 실무자의 윤리 역..", "thumbnail": "https://pimg.mk.co.kr/news/cms/202605/28/news-p.v1.20260528.460aece045e146789fd5b8700f07475f_R.png"}, {"title": "새마을금고재단, 푸르메재단과 ‘돌봄 사각’ 장애 가족에 2억원 지원", "link": "https://www.mk.co.kr/news/economy/12059691", "pubDate": "Thu, 28 May 2026 10:48:49 +09:00", "author": "매일경제", "description": "MG장애가족지원 사업 추진새마을금고가 장애아동뿐만 아니라 그동안 복지 사각지대에 놓여있던 ‘비장애 형제자매’의 심리치료까지 아우르는 종합적인 사회공헌 사업에 나선다. 단순한 일회성..", "thumbnail": "https://pimg.mk.co.kr/news/cms/202605/28/news-p.v1.20260528.4df37d2a37564e61a6fb0d679842d46c_R.jpg"}, {"title": "고환율이 떨어뜨린 은행 건전성…1분기 보통주자본비율 0.09%포인트 하락", "link": "https://www.mk.co.kr/news/economy/12059658", "pubDate": "Thu, 28 May 2026 10:26:35 +09:00", "author": "매일경제", "description": "모든 은행, 금융당국 규제비율 상회올해 1분기 국내은행의 국제결제은행(BIS) 기준 자본비율이 대출자산 증가와 원화값 하락 등의 영향으로 하락한 것으로 나타났다. 28일 금융감독원..", "thumbnail": "https://pimg.mk.co.kr/news/cms/202605/28/news-p.v1.20260317.9bb0fda7dd314461aae7b26949dc2cdd_R.jpg"}, {"title": "[단독] 자영업자 대출 41% 임대업 쏠림…고금리로 내몰리는 요식업", "link": "https://www.mk.co.kr/news/economy/12059656", "pubDate": "Thu, 28 May 2026 10:26:13 +09:00", "author": "매일경제", "description": "4대 은행 개인사업자 대출 상위 10개 업종 최근 3년간 ‘부동산업’ 40%대 수준 유지 담보 가치 높고 부실 위험 낮은 대출로 몰려 “매출·신용·현금흐름 대출 대폭 확대해야”4대..", "thumbnail": "https://pimg.mk.co.kr/news/cms/202605/28/news-p.v1.20251203.0f2abe9b7b4b450794caa5f8c6b65220_R.jpg"}, {"title": "[속보] 한국은행, 올해 성장률 전망치 2.0%→2.6% 상향 조정", "link": "https://www.mk.co.kr/news/economy/12059617", "pubDate": "Thu, 28 May 2026 09:53:48 +09:00", "author": "매일경제", "description": "한국은행이 올해 한국의 실질 국내총생산(GDP) 성장률을 기존 2.0%에서 2.6%으로 상향 조정했다. 내년은 2.1%로 전망했다. 한은은 28일 수정 경제전망을 발표, 올해 성장..", "thumbnail": "https://pimg.mk.co.kr/news/cms/202605/28/news-p.v1.20260528.628e256315b442499c9b86603a0c6906_R.jpg"}, {"title": "[속보] 한은 기준금리 연 2.50% 동결…8회 연속", "link": "https://www.mk.co.kr/news/economy/12059612", "pubDate": "Thu, 28 May 2026 09:51:16 +09:00", "author": "매일경제", "description": "중동전쟁 여파 불확실성 여전 성장률·소비자물가 상승률도 상향한국은행은 28일 금융통화위원회를 열고 현재 연 2.50%인 기준금리를 동결했다. 지난해 7·8·10·11월과 올해 1·..", "thumbnail": "https://pimg.mk.co.kr/news/cms/202605/28/news-p.v1.20260528.97086e7bdd804b03868d7f7791fad4b8_R.jpg"}, {"title": "김영훈 노동장관 “반도체는 공공재, 성과 사회적 배분 논의를”", "link": "https://www.mk.co.kr/news/economy/12059503", "pubDate": "Thu, 28 May 2026 06:42:08 +09:00", "author": "매일경제", "description": "파업 직전까지 갔던 삼성전자 사태를 계기로 정부가 대기업 초과이익의 재분배를 놓고 사회적 논의에 착수하기로 했다. 김영훈 고용노동부 장관은 반도체를 ‘공공재’로 규정하면서 천문학적..", "thumbnail": "https://pimg.mk.co.kr/news/cms/202605/28/rcv.YNA.20260527.PYH2026052708340001300_R.jpg"}, {"title": "사전투표 첫날 오전 11시 투표율 3.81%…4년 전보다 0.22%p 높아", "link": "https://www.hankyung.com/article/2026052964937", "pubDate": "Fri, 29 May 2026 11:22:41 +0900", "author": "한경우", "description": "", "thumbnail": ""}, {"title": "테슬라도 뚫었다…주7일 24시간 풀가동하는 로봇 유망주는?", "link": "https://www.hankyung.com/article/202605296152i", "pubDate": "Fri, 29 May 2026 11:21:53 +0900", "author": "민지혜", "description": "", "thumbnail": ""}, {"title": "직장에서 '독한 여자'가 되는 이유, 신간 <왜 여성은 일할수록 불리해질까>", "link": "https://www.hankyung.com/article/202605295814i", "pubDate": "Fri, 29 May 2026 11:21:26 +0900", "author": "허세민", "description": "", "thumbnail": ""}, {"title": "문재인 전 대통령 양산서 한표 행사…\"내란 세력 심판\"", "link": "https://www.hankyung.com/article/2026052962177", "pubDate": "Fri, 29 May 2026 11:20:37 +0900", "author": "김희선", "description": "", "thumbnail": ""}, {"title": "[속보] 블루오리진 로켓 연소시험중 대형 폭발…\"직원들은 무사\"", "link": "https://www.hankyung.com/article/2026052964797", "pubDate": "Fri, 29 May 2026 11:19:30 +0900", "author": "한경우", "description": "", "thumbnail": ""}, {"title": "파리크라상, 임직원 모금행사 '기부 앤 테이크' 진행…718명 참여", "link": "https://www.hankyung.com/article/202605296477g", "pubDate": "Fri, 29 May 2026 11:19:23 +0900", "author": "오세성", "description": "", "thumbnail": ""}, {"title": "'백인 우월주의' 피해 토머스 제퍼슨 저택에 숨어든 이웃들, 신간 <나의 몬티셀로>", "link": "https://www.hankyung.com/article/202605295560i", "pubDate": "Fri, 29 May 2026 11:18:17 +0900", "author": "최한종", "description": "", "thumbnail": ""}, {"title": "\"다시 앞서간다\"...초고수가 선택한 1위 반도체 기업은?", "link": "https://www.hankyung.com/article/202605296223i", "pubDate": "Fri, 29 May 2026 11:14:31 +0900", "author": "오현아", "description": "", "thumbnail": ""}, {"title": "에프앤가이드 지수 추종 ETF 순자산 77조원 돌파", "link": "https://www.hankyung.com/article/202605296437i", "pubDate": "Fri, 29 May 2026 11:12:28 +0900", "author": "박주연", "description": "", "thumbnail": ""}, {"title": "'재판 불출석 패소' 권경애 변호사, 6500만원 배상 판결 확정", "link": "https://www.hankyung.com/article/2026052964327", "pubDate": "Fri, 29 May 2026 11:11:44 +0900", "author": "한경우", "description": "", "thumbnail": ""}, {"title": "진중권 \"김관영 이기면 정청래에 치명타\"…與 \"당선돼도 복당 불가\"", "link": "https://www.hankyung.com/article/2026052959457", "pubDate": "Fri, 29 May 2026 11:10:57 +0900", "author": "이미나", "description": "", "thumbnail": ""}, {"title": "'재판 노쇼' 권경애, 6500만원 배상 확정…\"약정금도 추가로 지급해야\"", "link": "https://www.hankyung.com/article/202605296199i", "pubDate": "Fri, 29 May 2026 11:08:56 +0900", "author": "이인혁", "description": "", "thumbnail": ""}, {"title": "코스피, 종전 기대감에 장중 8400선 회복…LG씨엔에스 '上'", "link": "https://www.hankyung.com/article/2026052963756", "pubDate": "Fri, 29 May 2026 11:07:43 +0900", "author": "김연지", "description": "", "thumbnail": ""}, {"title": "흑석 2구역도 '7부 능선' 넘었다…49층·1045가구로 재탄생", "link": "https://www.hankyung.com/article/2026052963936", "pubDate": "Fri, 29 May 2026 11:06:34 +0900", "author": "이슬기", "description": "", "thumbnail": ""}, {"title": "사전투표 마친 정원오 \"박빙 승리 예상\" 오세훈 \"뒤집을 수 있다\"", "link": "https://www.hankyung.com/article/2026052960207", "pubDate": "Fri, 29 May 2026 10:59:57 +0900", "author": "김희선", "description": "", "thumbnail": ""}, {"title": "아홉, 작정한 첫 아시아 투어…신곡 선공개·커버 무대 예고", "link": "https://www.hankyung.com/article/202605296370H", "pubDate": "Fri, 29 May 2026 10:55:35 +0900", "author": "김수영", "description": "", "thumbnail": ""}, {"title": "中 반체제인사 둥광핑, 출입국관리소로 신병 인도", "link": "https://www.hankyung.com/article/2026052963777", "pubDate": "Fri, 29 May 2026 10:54:52 +0900", "author": "한경우", "description": "", "thumbnail": ""}, {"title": "발버둥치며 끝말잇기처럼 이어가는 삶, 문지혁 신간 <실전 한국어>", "link": "https://www.hankyung.com/article/202605295535i", "pubDate": "Fri, 29 May 2026 10:54:06 +0900", "author": "최한종", "description": "", "thumbnail": ""}, {"title": "토스뱅크, 1분기 순이익 296억원…전년比 58% 증가", "link": "https://www.hankyung.com/article/202605296361i", "pubDate": "Fri, 29 May 2026 10:50:08 +0900", "author": "김진성", "description": "", "thumbnail": ""}, {"title": "삼성이 콕 찍은 미래 먹거리 '이것'…파리서 베일 벗는다", "link": "https://www.hankyung.com/article/202605296345g", "pubDate": "Fri, 29 May 2026 10:48:19 +0900", "author": "홍민성", "description": "", "thumbnail": ""}, {"title": "'누적 기부액 210억' 김장훈 \"전혀 아깝지 않다\"", "link": "https://www.hankyung.com/article/202605296165H", "pubDate": "Fri, 29 May 2026 10:46:43 +0900", "author": "김수영", "description": "", "thumbnail": ""}, {"title": "법무장관 \"억울한 피해자 안 나오게 형사소송 제도 개선할 것\"", "link": "https://www.hankyung.com/article/2026052963377", "pubDate": "Fri, 29 May 2026 10:42:49 +0900", "author": "한경우", "description": "", "thumbnail": ""}, {"title": "홍콩거래소, IPO 1위 굳히려 상장 문턱 낮춘다 [박지윤의 글로벌 모니터]", "link": "https://www.hankyung.com/article/202605296310i", "pubDate": "Fri, 29 May 2026 10:42:24 +0900", "author": "박지윤", "description": "", "thumbnail": ""}, {"title": "같은 동네인데…한쪽은 76% 급등, 다른 쪽은 하락한 이유", "link": "https://www.hankyung.com/article/2026052960176", "pubDate": "Fri, 29 May 2026 10:42:08 +0900", "author": "이슬기", "description": "", "thumbnail": ""}, {"title": "안락사, 존엄사, 조력임종… 전부 다른 뜻인 거 아셨나요, 신간 <깨끗한 죽음이라는 환상>", "link": "https://www.hankyung.com/article/202605284772i", "pubDate": "Fri, 29 May 2026 10:42:05 +0900", "author": "설지연", "description": "", "thumbnail": ""}, {"title": "경찰, '서소문 고가 붕괴' 서울시·원청·하청 등 7곳 압수수색", "link": "https://www.hankyung.com/article/202605296271i", "pubDate": "Fri, 29 May 2026 10:38:57 +0900", "author": "우연수", "description": "", "thumbnail": ""}, {"title": "[마켓라이브] 코스피 1.59% 상승 중… 반도체·전자부품 강세, 외국인 매도세 지속 [오전10시 시황]", "link": "https://www.hankyung.com/article/202605296282i", "pubDate": "Fri, 29 May 2026 10:38:11 +0900", "author": "오현아", "description": "", "thumbnail": ""}, {"title": "파타고니아 창업자를 괴롭힌 '착한 기업' 딜레마, 신간 <더트백 억만장자>", "link": "https://www.hankyung.com/article/202605284759i", "pubDate": "Fri, 29 May 2026 10:37:17 +0900", "author": "최한종", "description": "", "thumbnail": ""}, {"title": "국민 3명 중 1명 \"소비에서 가장 중요한 분야는 식품·외식\"", "link": "https://www.hankyung.com/article/2026052963117", "pubDate": "Fri, 29 May 2026 10:36:58 +0900", "author": "한경우", "description": "", "thumbnail": ""}, {"title": "최태원 \"AI 인재, 공대생만 의미하는 것 아냐\"…미래 인재상은?", "link": "https://www.hankyung.com/article/202605295988g", "pubDate": "Fri, 29 May 2026 10:32:33 +0900", "author": "김대영", "description": "", "thumbnail": ""}, {"title": "“죽음도 정복”… 억만장자와 AI가 만났다, 신간 <불멸의 설계자들>", "link": "https://www.hankyung.com/article/202605284613i", "pubDate": "Fri, 29 May 2026 10:24:47 +0900", "author": "설지연", "description": "", "thumbnail": ""}, {"title": "형 공명도 놀라겠네…'육군 현역 복무' NCT 도영의 깜짝 근황", "link": "https://www.hankyung.com/article/2026052961877", "pubDate": "Fri, 29 May 2026 10:19:51 +0900", "author": "김예랑", "description": "", "thumbnail": ""}, {"title": "KB증권, 저출생 극복 위해 '위기임산부' 3년째 지원", "link": "https://www.hankyung.com/article/2026052961626", "pubDate": "Fri, 29 May 2026 10:13:20 +0900", "author": "고정삼", "description": "", "thumbnail": ""}, {"title": "LG생건 피지오겔, 남성용 '아쿠아 포맨 오일컷 선스틱' 출시", "link": "https://www.hankyung.com/article/202605296155g", "pubDate": "Fri, 29 May 2026 10:07:24 +0900", "author": "오세성", "description": "", "thumbnail": ""}, {"title": "화장대에도 '여름옷'이 필요하다…무더위 속 내 피부 지키는 법 [정호석의 K-뷰티인사이트]", "link": "https://www.hankyung.com/article/202605269091i", "pubDate": "Fri, 29 May 2026 10:03:52 +0900", "author": "정호석", "description": "", "thumbnail": ""}, {"title": "\"사람 없나요?\"…공장서 일하던 로봇 고장나면 벌어지는 일 [도쿄나우]", "link": "https://www.hankyung.com/article/202605296081i", "pubDate": "Fri, 29 May 2026 10:00:38 +0900", "author": "도쿄=최만수", "description": "", "thumbnail": ""}, {"title": "\"씨젠, 비호흡기 진단으로 체질 변화 성공 ... 수익성도 더 개선될 것\"", "link": "https://www.hankyung.com/article/202605295788i", "pubDate": "Fri, 29 May 2026 10:00:01 +0900", "author": "최지희", "description": "", "thumbnail": ""}, {"title": "점심 먹고 '드립커피' 즐겨 마셨는데…영수증 보고 '깜짝' [프라이스&]", "link": "https://www.hankyung.com/article/202605295968i", "pubDate": "Fri, 29 May 2026 10:00:01 +0900", "author": "권용훈", "description": "", "thumbnail": ""}, {"title": "헬릭스미스 유전자치료제 '엔젠시스' 中 품목허가 획득", "link": "https://www.hankyung.com/article/202605296057i", "pubDate": "Fri, 29 May 2026 09:57:52 +0900", "author": "이우상", "description": "", "thumbnail": ""}, {"title": "中외교부장, 유엔 회의서 \"AI 군사 응용에 가드레일 설정해야\"", "link": "https://www.hankyung.com/article/2026052961007", "pubDate": "Fri, 29 May 2026 09:55:40 +0900", "author": "한경우", "description": "", "thumbnail": ""}, {"title": "외국인 보유 국내주택 10만8231가구…'중국인 56.8%'", "link": "https://www.hankyung.com/article/202605296099i", "pubDate": "Fri, 29 May 2026 09:54:36 +0900", "author": "유오상", "description": "", "thumbnail": ""}, {"title": "정청래, 마포서 사전투표 완료…장동혁은 '본투표'", "link": "https://www.hankyung.com/article/2026052959207", "pubDate": "Fri, 29 May 2026 09:51:15 +0900", "author": "김희선", "description": "", "thumbnail": ""}, {"title": "\"비타민 먹다 뚜껑을\"…30대 시의원 후보 응급실행", "link": "https://www.hankyung.com/article/2026052958737", "pubDate": "Fri, 29 May 2026 09:49:45 +0900", "author": "신현보", "description": "", "thumbnail": ""}, {"title": "국민성장펀드, 퓨리오사AI 8000억 투자 소식에…TS·DSC인베 '불기둥'", "link": "https://www.hankyung.com/article/2026052960546", "pubDate": "Fri, 29 May 2026 09:47:34 +0900", "author": "고정삼", "description": "", "thumbnail": ""}, {"title": "\"네이버와 AI 사업 겹쳤다\"…하정우 '업스테이지 지분 100억' 미스터리", "link": "https://www.hankyung.com/article/202605272031i", "pubDate": "Fri, 29 May 2026 09:43:39 +0900", "author": "이시은", "description": "", "thumbnail": ""}, {"title": "삼성전자 93%까지 추격한 하이닉스 시총…역전 가능성 따져보니", "link": "https://www.hankyung.com/article/202605295681i", "pubDate": "Fri, 29 May 2026 09:39:56 +0900", "author": "조재길", "description": "", "thumbnail": ""}, {"title": "삼성전기, 장 초반 7%대 급등…\"200만원 눈앞\"", "link": "https://www.hankyung.com/article/2026052959956", "pubDate": "Fri, 29 May 2026 09:37:30 +0900", "author": "김연지", "description": "", "thumbnail": ""}, {"title": "투썸플레이스, 크런치 초코볼 더한 '떠먹는 아박' 신메뉴 출시", "link": "https://www.hankyung.com/article/202605296019g", "pubDate": "Fri, 29 May 2026 09:37:21 +0900", "author": "오세성", "description": "", "thumbnail": ""}, {"title": "'제2의 깐부회동' 열리나…젠슨 황 방한 기대감에 LG·네이버·현대오토↑", "link": "https://www.hankyung.com/article/2026052958926", "pubDate": "Fri, 29 May 2026 09:35:39 +0900", "author": "이수", "description": "", "thumbnail": ""}, {"title": "삼성전자·SK하닉도 베팅했다…오픈AI 제친 '대어' 정체", "link": "https://www.hankyung.com/article/202605295806g", "pubDate": "Fri, 29 May 2026 09:33:31 +0900", "author": "홍민성", "description": "", "thumbnail": ""}]