[{"title": "사지 묶인 환자, 다른 환자 폭행에 사망…관리 소홀 병원장 처벌은?", "link": "https://www.hankyung.com/article/2026071327187", "pubDate": "Mon, 13 Jul 2026 19:40:33 +0900", "author": "이보배", "description": "", "thumbnail": ""}, {"title": "경산 살인사건 '초동 부실' 공방…경찰, 분단위 타임라인 반박", "link": "https://www.hankyung.com/article/2026071327167", "pubDate": "Mon, 13 Jul 2026 19:37:08 +0900", "author": "이정우", "description": "", "thumbnail": ""}, {"title": "\"고려아연, 작년 주총서 영풍 의결권 제한 위법\"", "link": "https://www.hankyung.com/article/2026071327281", "pubDate": "Mon, 13 Jul 2026 19:34:14 +0900", "author": "김유진", "description": "", "thumbnail": ""}, {"title": "[속보] 정교유착 합수본, '국힘 당원가입 강요' 이만희 구속기소", "link": "https://www.hankyung.com/article/2026071327247", "pubDate": "Mon, 13 Jul 2026 19:29:00 +0900", "author": "이정우", "description": "", "thumbnail": ""}, {"title": "\"SK하이닉스, 모두가 흔들고 싶은 돈나무 돼\" [블룸버그]", "link": "https://www.hankyung.com/article/202607132712i", "pubDate": "Mon, 13 Jul 2026 19:22:36 +0900", "author": "김정아", "description": "", "thumbnail": ""}, {"title": "\"36년 내공 담았다\"…10여개국 수출길 뚫은 '이 음료'", "link": "https://www.hankyung.com/article/202607132707i", "pubDate": "Mon, 13 Jul 2026 19:13:05 +0900", "author": "권용훈", "description": "", "thumbnail": ""}, {"title": "오세훈, 14일 국무회의 참석…서울 부동산 민심 전달한다", "link": "https://www.hankyung.com/article/2026071327037", "pubDate": "Mon, 13 Jul 2026 19:11:31 +0900", "author": "이정우", "description": "", "thumbnail": ""}, {"title": "국제유가 상승에 美국채금리도 ↑…美주가선물 하락", "link": "https://www.hankyung.com/article/202607132684i", "pubDate": "Mon, 13 Jul 2026 19:09:43 +0900", "author": "김정아", "description": "", "thumbnail": ""}, {"title": "\"물 반 사람 반\"…2030 몰린 '5000원 흠뻑쇼' 정체 [트렌드+]", "link": "https://www.hankyung.com/article/202607131610H", "pubDate": "Mon, 13 Jul 2026 19:02:01 +0900", "author": "박수빈", "description": "", "thumbnail": ""}, {"title": "앱 켜고 \"예약 알려줘, 무슨 메뉴 맛있어?\"…확 달라진 '네이버 검색'", "link": "https://www.hankyung.com/article/202607132028g", "pubDate": "Mon, 13 Jul 2026 19:00:06 +0900", "author": "김대영", "description": "", "thumbnail": ""}, {"title": "\"전기료도 내기 힘들어\"…홈플러스 28년 만에 역사속으로", "link": "https://www.hankyung.com/article/2026071324791", "pubDate": "Mon, 13 Jul 2026 19:00:04 +0900", "author": "오형주", "description": "", "thumbnail": ""}, {"title": "[속보]대한항공, 아시아나티앤아이 청산 추진", "link": "https://www.hankyung.com/article/202607132674i", "pubDate": "Mon, 13 Jul 2026 18:57:22 +0900", "author": "신정은", "description": "", "thumbnail": ""}, {"title": "검찰 보완수사가 밝힌 370억…'깡통코인' 일당 구속기소", "link": "https://www.hankyung.com/article/2026071326827", "pubDate": "Mon, 13 Jul 2026 18:51:35 +0900", "author": "이정우", "description": "", "thumbnail": ""}, {"title": "40년 난제 '암세포 성장 스위치'…공략 실마리 찾았다", "link": "https://www.hankyung.com/article/2026071325921", "pubDate": "Mon, 13 Jul 2026 18:51:28 +0900", "author": "김유림", "description": "", "thumbnail": ""}, {"title": "대웅제약 톡신 '나보타' 누적 매출 1조원 달성", "link": "https://www.hankyung.com/article/2026071325931", "pubDate": "Mon, 13 Jul 2026 18:48:49 +0900", "author": "이민형", "description": "", "thumbnail": ""}, {"title": "클래시스 \"고주파기기 공략 강화…국내 매출 2000억 목표\"", "link": "https://www.hankyung.com/article/2026071325951", "pubDate": "Mon, 13 Jul 2026 18:48:03 +0900", "author": "이민형", "description": "", "thumbnail": ""}, {"title": "페니트리움 항암 신약 美 임상 속도 빨라진다", "link": "https://www.hankyung.com/article/2026071325941", "pubDate": "Mon, 13 Jul 2026 18:46:35 +0900", "author": "이우상", "description": "", "thumbnail": ""}, {"title": "80년 '위계 문화' 허물고 혁신 구축한 이한우", "link": "https://www.hankyung.com/article/2026071325111", "pubDate": "Mon, 13 Jul 2026 18:45:44 +0900", "author": "이유정", "description": "", "thumbnail": ""}, {"title": "LG전자, GS건설 손잡고 차세대 'AI 홈' 개발 속도", "link": "https://www.hankyung.com/article/2026071325121", "pubDate": "Mon, 13 Jul 2026 18:43:57 +0900", "author": "원종환", "description": "", "thumbnail": ""}, {"title": "대한항공, 고유가·고환율에도 실적 선방", "link": "https://www.hankyung.com/article/2026071325181", "pubDate": "Mon, 13 Jul 2026 18:43:06 +0900", "author": "노유정", "description": "", "thumbnail": ""}, {"title": "남미로 간 K방산…현대로템·KAI, 페루 수출 '청신호'", "link": "https://www.hankyung.com/article/2026071325151", "pubDate": "Mon, 13 Jul 2026 18:42:40 +0900", "author": "안시욱", "description": "", "thumbnail": ""}, {"title": "코오롱인더, 반도체·디스플레이 소재 매각", "link": "https://www.hankyung.com/article/2026071325171", "pubDate": "Mon, 13 Jul 2026 18:40:18 +0900", "author": "신정은", "description": "", "thumbnail": ""}, {"title": "삼성전자 노조 \"호남 반도체도 교섭 대상\"", "link": "https://www.hankyung.com/article/2026071325161", "pubDate": "Mon, 13 Jul 2026 18:39:40 +0900", "author": "강해령", "description": "", "thumbnail": ""}, {"title": "[포토] 현대차, TCR 월드투어 시즌 3승", "link": "https://www.hankyung.com/article/2026071325131", "pubDate": "Mon, 13 Jul 2026 18:39:24 +0900", "author": "한국경제 | 전체뉴스", "description": "", "thumbnail": ""}, {"title": "[포토] 포성 여전한 가자지구", "link": "https://www.hankyung.com/article/2026071325901", "pubDate": "Mon, 13 Jul 2026 18:33:11 +0900", "author": "한국경제 | 전체뉴스", "description": "", "thumbnail": ""}, {"title": "[포토] 태국 방콕서 화재…27명 사망", "link": "https://www.hankyung.com/article/2026071325891", "pubDate": "Mon, 13 Jul 2026 18:31:50 +0900", "author": "한국경제 | 전체뉴스", "description": "", "thumbnail": ""}, {"title": "'코코넛 시드' 열풍…스타창업자, 로봇기업 세우자마자 수백억 유치", "link": "https://www.hankyung.com/article/2026071325051", "pubDate": "Mon, 13 Jul 2026 18:30:20 +0900", "author": "남준우", "description": "", "thumbnail": ""}, {"title": "[단독] SK하이닉스, 호남팹 합작 투자 가능…수십조 재무부담 던다", "link": "https://www.hankyung.com/article/2026071325621", "pubDate": "Mon, 13 Jul 2026 18:30:04 +0900", "author": "이시은", "description": "", "thumbnail": ""}, {"title": "[단독] 호남팹 속도전 '증손회사 100%룰' 푼다", "link": "https://www.hankyung.com/article/2026071325491", "pubDate": "Mon, 13 Jul 2026 18:30:01 +0900", "author": "이시은", "description": "", "thumbnail": ""}, {"title": "\"코스피 PER 역사적 저점 근접…美 빅테크 실적 발표가 변곡점\"", "link": "https://www.hankyung.com/article/2026071325701", "pubDate": "Mon, 13 Jul 2026 18:26:17 +0900", "author": "강진규", "description": "", "thumbnail": ""}, {"title": "미국산 신선란 가격 인하…이마트서 30구 5890원→4980원", "link": "https://www.hankyung.com/article/2026071326567", "pubDate": "Mon, 13 Jul 2026 18:25:22 +0900", "author": "이보배", "description": "", "thumbnail": ""}, {"title": "국힘, PK서 무슨 일…지지율 20%P 급락", "link": "https://www.hankyung.com/article/2026071325741", "pubDate": "Mon, 13 Jul 2026 18:23:39 +0900", "author": "이슬기", "description": "", "thumbnail": ""}, {"title": "송영길 \"정청래 얼굴로 총선 이기겠나…딸·아들도 안 찍어\"", "link": "https://www.hankyung.com/article/2026071326587", "pubDate": "Mon, 13 Jul 2026 18:23:37 +0900", "author": "이정우", "description": "", "thumbnail": ""}, {"title": "당정 \"메가프로젝트 추진 속도\"…신규 원전 건설 가능성 열어둬", "link": "https://www.hankyung.com/article/2026071325761", "pubDate": "Mon, 13 Jul 2026 18:22:43 +0900", "author": "하지은", "description": "", "thumbnail": ""}, {"title": "韓·美·日, SMR 뭉친다…\"패키지 사업 공동수주\"", "link": "https://www.hankyung.com/article/2026071325771", "pubDate": "Mon, 13 Jul 2026 18:22:05 +0900", "author": "김다빈", "description": "", "thumbnail": ""}, {"title": "삼전닉스 레버리지, 일제히 최저가로 추락", "link": "https://www.hankyung.com/article/2026071325721", "pubDate": "Mon, 13 Jul 2026 18:20:40 +0900", "author": "심우일", "description": "", "thumbnail": ""}, {"title": "하이닉스 '역김치 프리미엄' 현실 됐다", "link": "https://www.hankyung.com/article/2026071325711", "pubDate": "Mon, 13 Jul 2026 18:19:56 +0900", "author": "이선아", "description": "", "thumbnail": ""}, {"title": "FSN, K뷰티 브랜드 '기픈' 출시…\"사업 포트폴리오 확대\"", "link": "https://www.hankyung.com/article/202607132183g", "pubDate": "Mon, 13 Jul 2026 18:18:08 +0900", "author": "박수림", "description": "", "thumbnail": ""}, {"title": "7말8초 부동산 대책, 대출규제 완화에 관심…실수요자 숨통 트이나", "link": "https://www.hankyung.com/article/2026071325671", "pubDate": "Mon, 13 Jul 2026 18:17:30 +0900", "author": "조미현", "description": "", "thumbnail": ""}, {"title": "신용한도 줄이고 모기지보험 제한…지방銀도 줄줄이 '대출 빗장'", "link": "https://www.hankyung.com/article/2026071325661", "pubDate": "Mon, 13 Jul 2026 18:16:52 +0900", "author": "배태웅", "description": "", "thumbnail": ""}, {"title": "별도법인이 설비 마련…하이닉스는 사용료만", "link": "https://www.hankyung.com/article/2026071325611", "pubDate": "Mon, 13 Jul 2026 18:15:58 +0900", "author": "하지은", "description": "", "thumbnail": ""}, {"title": "내년 예산 '800조+α' 슈퍼 확장재정", "link": "https://www.hankyung.com/article/2026071325601", "pubDate": "Mon, 13 Jul 2026 18:15:20 +0900", "author": "한재영", "description": "", "thumbnail": ""}, {"title": "신한금융그룹, 2026 신한장학캠프 개최", "link": "https://www.hankyung.com/article/2026071326091", "pubDate": "Mon, 13 Jul 2026 18:13:01 +0900", "author": "오유림", "description": "", "thumbnail": ""}, {"title": "유해란·김주형 나란히 우승컵…'퍼펙트 코리안 데이'", "link": "https://www.hankyung.com/article/2026071325561", "pubDate": "Mon, 13 Jul 2026 18:12:27 +0900", "author": "조수영", "description": "", "thumbnail": ""}, {"title": "주담대 연간 한도 다 찼다… '대출 절벽' 현실화되나 [퇴근길 30초 경제]", "link": "https://www.hankyung.com/article/202607132649H", "pubDate": "Mon, 13 Jul 2026 18:12:25 +0900", "author": "변성현", "description": "", "thumbnail": ""}, {"title": "안으로 깊어지는 도시 '서울' [한경 프리미엄9 TODAY]", "link": "https://www.hankyung.com/article/2026071325571", "pubDate": "Mon, 13 Jul 2026 18:10:02 +0900", "author": "한국경제 | 전체뉴스", "description": "", "thumbnail": ""}, {"title": "이창무 한양대 교수 \"인문학도 꿈꾼 공대생…이제 서울의 미래 그리죠\"", "link": "https://www.hankyung.com/article/2026071326151", "pubDate": "Mon, 13 Jul 2026 18:09:57 +0900", "author": "박종필", "description": "", "thumbnail": ""}, {"title": "삼성전자, 임원 928명에 자사주 3200억원 지급…1인당 3.5억원꼴", "link": "https://www.hankyung.com/article/2026071325297", "pubDate": "Mon, 13 Jul 2026 18:08:09 +0900", "author": "이정우", "description": "", "thumbnail": ""}, {"title": "편집인협회기금, 석좌교수제 시행", "link": "https://www.hankyung.com/article/2026071326131", "pubDate": "Mon, 13 Jul 2026 18:07:58 +0900", "author": "한국경제 | 전체뉴스", "description": "", "thumbnail": ""}, {"title": "교보생명, 유소년 체육 42년째 후원", "link": "https://www.hankyung.com/article/2026071326121", "pubDate": "Mon, 13 Jul 2026 18:07:38 +0900", "author": "한국경제 | 전체뉴스", "description": "", "thumbnail": ""}]