[{"title": "사우디 증산·가격 인하 카드…중동 원유 시장 점유율 전쟁", "link": "https://www.hankyung.com/article/202607081578i", "pubDate": "Wed, 08 Jul 2026 07:49:24 +0900", "author": "김주완", "description": "", "thumbnail": ""}, {"title": "회식 줄었는데 소주는 더 팔렸다…요즘 2030 달려가는 곳 [권용훈의 트렌드워치]", "link": "https://www.hankyung.com/article/202607023004i", "pubDate": "Wed, 08 Jul 2026 06:00:11 +0900", "author": "권용훈", "description": "", "thumbnail": ""}, {"title": "한 달새 1만대 '대박'…\"성공하면 탄다\" 국민 세단의 귀환", "link": "https://www.hankyung.com/article/202607070558g", "pubDate": "Wed, 08 Jul 2026 06:00:01 +0900", "author": "최수진", "description": "", "thumbnail": ""}, {"title": "트럼프, 또 \"그린란드 미국이 통제해야, 유럽 계속 반발시 미군 철수\" 위협", "link": "https://www.hankyung.com/article/202607081395i", "pubDate": "Wed, 08 Jul 2026 01:25:21 +0900", "author": "김정아", "description": "", "thumbnail": ""}, {"title": "블랙록도 나스닥100 추종 ETF 출시", "link": "https://www.hankyung.com/article/202607081386i", "pubDate": "Wed, 08 Jul 2026 00:52:57 +0900", "author": "김정아", "description": "", "thumbnail": ""}, {"title": "AI 투자 우려에도…아마존 \"38조원 더\" 채권 발행", "link": "https://www.hankyung.com/article/202607071375i", "pubDate": "Wed, 08 Jul 2026 00:09:01 +0900", "author": "김정아", "description": "", "thumbnail": ""}, {"title": "태평양 건너 삼전 급락에 美 반도체주 매도…나스닥 1.3%↓", "link": "https://www.hankyung.com/article/202607071365i", "pubDate": "Tue, 07 Jul 2026 23:35:08 +0900", "author": "김정아", "description": "", "thumbnail": ""}, {"title": "\"딥시크, 자체 추론 AI칩 개발 중\"…\"중국외 글로벌 영향은 없어\" [로이터]", "link": "https://www.hankyung.com/article/202607071349i", "pubDate": "Tue, 07 Jul 2026 22:52:43 +0900", "author": "김정아", "description": "", "thumbnail": ""}, {"title": "모건스탠리 \"반도체대신 하이퍼스케일러\" 외쳤지만…블룸버그 \"맥7 지배 끝나\"", "link": "https://www.hankyung.com/article/202607071312i", "pubDate": "Tue, 07 Jul 2026 22:16:57 +0900", "author": "김정아", "description": "", "thumbnail": ""}, {"title": "美 5월 무역적자 118조원…14개월 만에 최대", "link": "https://www.hankyung.com/article/202607071328i", "pubDate": "Tue, 07 Jul 2026 22:08:49 +0900", "author": "김정아", "description": "", "thumbnail": ""}, {"title": "스페이스X, 오늘 나스닥100 편입…수십억달러 매수 촉발", "link": "https://www.hankyung.com/article/202607071246i", "pubDate": "Tue, 07 Jul 2026 21:19:24 +0900", "author": "김정아", "description": "", "thumbnail": ""}, {"title": "[단독] '中 컨테이너 담합' 美가 기소하자 韓도 가세…국내 해운사 배상 받을까", "link": "https://www.hankyung.com/article/2026070710941", "pubDate": "Tue, 07 Jul 2026 21:00:05 +0900", "author": "박종관", "description": "", "thumbnail": ""}, {"title": "[단독] 韓, 中 컨테이너 '54조 담합' 조사", "link": "https://www.hankyung.com/article/2026070710581", "pubDate": "Tue, 07 Jul 2026 21:00:03 +0900", "author": "박종관", "description": "", "thumbnail": ""}, {"title": "\"당연히 더 쌀 줄 알았는데\"…묶음상품 꺼리게 된 의외의 이유 [트렌드+]", "link": "https://www.hankyung.com/article/202607070507g", "pubDate": "Tue, 07 Jul 2026 20:00:04 +0900", "author": "박상경", "description": "", "thumbnail": ""}, {"title": "[포토] 한반도 농산물 관측 '농림위성' 우주로", "link": "https://www.hankyung.com/article/2026070712531", "pubDate": "Tue, 07 Jul 2026 19:47:14 +0900", "author": "오현아", "description": "", "thumbnail": ""}, {"title": "[단독] 54조원 피해…공정위, 中 컨테이너 가격 담합 조사 착수", "link": "https://www.hankyung.com/article/202607071234i", "pubDate": "Tue, 07 Jul 2026 19:22:46 +0900", "author": "박종관, 노유정", "description": "", "thumbnail": ""}, {"title": "[속보] 차세대 중형위성 4호, 발사 후 해외 지상국과 교신 성공", "link": "https://www.hankyung.com/article/2026070712327", "pubDate": "Tue, 07 Jul 2026 19:18:44 +0900", "author": "이수", "description": "", "thumbnail": ""}, {"title": "\"한국증시 때문\"에…블랙록·뱅가드 신흥시장ETF 희비엇갈려", "link": "https://www.hankyung.com/article/202607071220i", "pubDate": "Tue, 07 Jul 2026 19:15:50 +0900", "author": "김정아", "description": "", "thumbnail": ""}, {"title": "[속보] 차세대 중형위성 4호 발사체서 정상 분리…궤도 투입", "link": "https://www.hankyung.com/article/2026070712137", "pubDate": "Tue, 07 Jul 2026 18:44:44 +0900", "author": "이수", "description": "", "thumbnail": ""}, {"title": "\"AI 중심으로 모든 업무 재설계해야 생존\"", "link": "https://www.hankyung.com/article/2026070709591", "pubDate": "Tue, 07 Jul 2026 18:30:42 +0900", "author": "김대영", "description": "", "thumbnail": ""}, {"title": "동국제강 창립 72주년…장세욱 \"재창립 각오 혁신\"", "link": "https://www.hankyung.com/article/2026070710431", "pubDate": "Tue, 07 Jul 2026 18:25:38 +0900", "author": "안시욱", "description": "", "thumbnail": ""}, {"title": "SM그룹 대한해운 대표 민상기 前 건대총장 선임", "link": "https://www.hankyung.com/article/2026070710421", "pubDate": "Tue, 07 Jul 2026 18:24:10 +0900", "author": "노유정", "description": "", "thumbnail": ""}, {"title": "\"축제만으론 안 된다\"…우르르 몰린 관광객들 돈 쓰는 곳", "link": "https://www.hankyung.com/article/202607071136H", "pubDate": "Tue, 07 Jul 2026 18:17:34 +0900", "author": "신현보", "description": "", "thumbnail": ""}, {"title": "최저임금 노사 격차 990원 좁혔지만…'줄다리기' 지속", "link": "https://www.hankyung.com/article/202607071139i", "pubDate": "Tue, 07 Jul 2026 18:13:54 +0900", "author": "정희원", "description": "", "thumbnail": ""}, {"title": "상폐 위기인데 주가는 급등…'25년 선행'이 살린 기업", "link": "https://www.hankyung.com/article/2026070711697", "pubDate": "Tue, 07 Jul 2026 18:10:41 +0900", "author": "장지민", "description": "", "thumbnail": ""}, {"title": "글로벌 패권전쟁 속 공격수단 된 경쟁법", "link": "https://www.hankyung.com/article/2026070710981", "pubDate": "Tue, 07 Jul 2026 18:07:38 +0900", "author": "박종관", "description": "", "thumbnail": ""}, {"title": "삼성화재, 대학생 광고대회 후원 참여", "link": "https://www.hankyung.com/article/2026070710801", "pubDate": "Tue, 07 Jul 2026 18:00:26 +0900", "author": "오현아", "description": "", "thumbnail": ""}, {"title": "현대엘리베이터 학용품 기부 봉사활동", "link": "https://www.hankyung.com/article/2026070710811", "pubDate": "Tue, 07 Jul 2026 18:00:02 +0900", "author": "조아라", "description": "", "thumbnail": ""}, {"title": "가계부채비율 8년 만에 최저…GDP 급증에 '착시효과'", "link": "https://www.hankyung.com/article/2026070710681", "pubDate": "Tue, 07 Jul 2026 17:58:34 +0900", "author": "심성미", "description": "", "thumbnail": ""}, {"title": "'전분당 담합' 4社에 과징금 7476억", "link": "https://www.hankyung.com/article/2026070710671", "pubDate": "Tue, 07 Jul 2026 17:58:08 +0900", "author": "박종관", "description": "", "thumbnail": ""}, {"title": "2주택자 양도세 피하려…엄마 친구와 '가짜 매매'", "link": "https://www.hankyung.com/article/2026070710661", "pubDate": "Tue, 07 Jul 2026 17:57:55 +0900", "author": "김일규", "description": "", "thumbnail": ""}, {"title": "성능보다 안보동맹…나토 벽에 막힌 K잠수함", "link": "https://www.hankyung.com/article/2026070710641", "pubDate": "Tue, 07 Jul 2026 17:57:01 +0900", "author": "신정은", "description": "", "thumbnail": ""}, {"title": "현대차그룹, 협력사 자금 조달 지원", "link": "https://www.hankyung.com/article/2026070710851", "pubDate": "Tue, 07 Jul 2026 17:56:20 +0900", "author": "정상원", "description": "", "thumbnail": ""}, {"title": "소비자물가지수 품목 교체…마라탕·챗GPT 넣고 땅콩·도라지 뺀다", "link": "https://www.hankyung.com/article/2026070710161", "pubDate": "Tue, 07 Jul 2026 17:49:21 +0900", "author": "김익환", "description": "", "thumbnail": ""}, {"title": "LG엔솔, ESS·전기차 판매 호조에 '흑자전환'", "link": "https://www.hankyung.com/article/2026070709631", "pubDate": "Tue, 07 Jul 2026 17:48:14 +0900", "author": "김우섭", "description": "", "thumbnail": ""}, {"title": "'89조' 삼전 역대급 실적 내놓은 날…또 터진 '메모리 고점론'", "link": "https://www.hankyung.com/article/2026070710611", "pubDate": "Tue, 07 Jul 2026 17:47:30 +0900", "author": "강해령", "description": "", "thumbnail": ""}, {"title": "내년엔 영업이익 500조 예상...엔비디아·구글 꺾은 삼성전자 [퇴근길 30초 경제]", "link": "https://www.hankyung.com/article/2026070710757", "pubDate": "Tue, 07 Jul 2026 17:47:15 +0900", "author": "김영석", "description": "", "thumbnail": ""}, {"title": "EU, 韓 타이어 반덤핑 관세 '최고 24.4% 부과' 확정", "link": "https://www.hankyung.com/article/2026070710401", "pubDate": "Tue, 07 Jul 2026 17:46:53 +0900", "author": "양길성", "description": "", "thumbnail": ""}, {"title": "정부 '초장기 기술펀드' 대기업 계열사도 투자", "link": "https://www.hankyung.com/article/2026070710471", "pubDate": "Tue, 07 Jul 2026 17:46:22 +0900", "author": "서형교", "description": "", "thumbnail": ""}, {"title": "이재용, 美 선밸리로 출국…AI 공급망 논의", "link": "https://www.hankyung.com/article/2026070710391", "pubDate": "Tue, 07 Jul 2026 17:46:07 +0900", "author": "원종환", "description": "", "thumbnail": ""}, {"title": "\"수천시간 비행 거뜬\"…한화, K무인기 엔진 첫 공개", "link": "https://www.hankyung.com/article/2026070710451", "pubDate": "Tue, 07 Jul 2026 17:44:55 +0900", "author": "송준영", "description": "", "thumbnail": ""}, {"title": "LG전자, 매출·영업익 2분기 기준 사상 최대", "link": "https://www.hankyung.com/article/2026070710441", "pubDate": "Tue, 07 Jul 2026 17:44:19 +0900", "author": "원종환", "description": "", "thumbnail": ""}, {"title": "세계서 가장 돈 많이 버는 기업 삼성전자", "link": "https://www.hankyung.com/article/2026070710541", "pubDate": "Tue, 07 Jul 2026 17:43:55 +0900", "author": "강해령", "description": "", "thumbnail": ""}, {"title": "내년 공기관 CCTV 대란 오나", "link": "https://www.hankyung.com/article/2026070710261", "pubDate": "Tue, 07 Jul 2026 17:43:48 +0900", "author": "성상훈", "description": "", "thumbnail": ""}, {"title": "\"번역기 돌리던 해외 구매는 끝\"", "link": "https://www.hankyung.com/article/2026070709691", "pubDate": "Tue, 07 Jul 2026 17:42:35 +0900", "author": "고은이", "description": "", "thumbnail": ""}, {"title": "\"車시장 성장 한계\"…부품사 30곳 '로봇기업' 대변신", "link": "https://www.hankyung.com/article/2026070709951", "pubDate": "Tue, 07 Jul 2026 17:42:13 +0900", "author": "양길성", "description": "", "thumbnail": ""}, {"title": "유럽 폭염에 튀김유값 급등", "link": "https://www.hankyung.com/article/2026070709651", "pubDate": "Tue, 07 Jul 2026 17:41:13 +0900", "author": "권용훈", "description": "", "thumbnail": ""}, {"title": "삼전닉스 단일종목 레버리지 폭락…대부분 상장가 밑으로", "link": "https://www.hankyung.com/article/2026070709187", "pubDate": "Tue, 07 Jul 2026 17:40:22 +0900", "author": "이수", "description": "", "thumbnail": ""}, {"title": "빽다방, 8월 도쿄에 1호점…글로벌 시장 공략 본격화", "link": "https://www.hankyung.com/article/2026070709711", "pubDate": "Tue, 07 Jul 2026 17:40:02 +0900", "author": "고은이", "description": "", "thumbnail": ""}, {"title": "하나투어 신임 CEO에 조좌진 前 롯데카드 대표", "link": "https://www.hankyung.com/article/2026070709721", "pubDate": "Tue, 07 Jul 2026 17:39:22 +0900", "author": "오형주", "description": "", "thumbnail": ""}]